coc-ccg.db
coc-lcg.db
cthulhucli.py
cthulhucli-1.0.5.dist-info/METADATA
cthulhucli-1.0.5.dist-info/WHEEL
cthulhucli-1.0.5.dist-info/entry_points.txt
cthulhucli-1.0.5.dist-info/licenses/LICENSE.txt
cthulhucli-1.0.5.dist-info/RECORD
