Metadata-Version: 2.4
Name: cthulhucli
Version: 1.0.5
Summary: A command line interface for browsing cards from the Call of Cthulhu CCG and LCG.
Project-URL: Homepage, https://github.com/jimorie/cthulhucli
Author-email: Petter Nyström <jimorie@gmail.com>
License-File: LICENSE.txt
Keywords: call of cthulhu,ccg,cthulhu,lcg
Requires-Python: >=3.6
Requires-Dist: click<9.0,>=8.1.6
Requires-Dist: clicksearch<1.0,>=0.5.0
Provides-Extra: dev
Requires-Dist: black; extra == 'dev'
Requires-Dist: build; extra == 'dev'
Requires-Dist: bump; extra == 'dev'
Requires-Dist: hatchling; extra == 'dev'
Requires-Dist: ruff; extra == 'dev'
Requires-Dist: twine; extra == 'dev'
